ViteLicense/__init__.py
ViteLicense/core.py
tests/__init__.py
tests/computer.py
tests/validate.py
ViteLicense-1.0.9.dist-info/LICENSE.md
ViteLicense-1.0.9.dist-info/METADATA
ViteLicense-1.0.9.dist-info/WHEEL
ViteLicense-1.0.9.dist-info/top_level.txt
ViteLicense-1.0.9.dist-info/RECORD
